ehd/__init__.py
Njeru-0.0.1.dist-info/LICENSE
Njeru-0.0.1.dist-info/METADATA
Njeru-0.0.1.dist-info/WHEEL
Njeru-0.0.1.dist-info/top_level.txt
Njeru-0.0.1.dist-info/RECORD
