Metadata-Version: 2.1
Name: Njeru
Version: 0.0.1
Summary: To use for my projects
Home-page: https://github.com/Denisnjeru/EHD.git
Author: Njeru
Author-email: njerudenis0@gmail.com
License: UNKNOWN
Platform: UNKNOWN
Classifier: Programming Language :: Python :: 3
Classifier: License :: OSI Approved :: MIT License
Classifier: Operating System :: OS Independent
Requires-Python: >=3.*
